pospell.py
pospell-1.3.dist-info/METADATA
pospell-1.3.dist-info/WHEEL
pospell-1.3.dist-info/entry_points.txt
pospell-1.3.dist-info/top_level.txt
pospell-1.3.dist-info/RECORD
