Metadata-Version: 2.1
Name: pospell
Version: 1.3
Summary: Spellcheck .po files containing reStructuredText translations
Author-email: Julien Palard <julien@palard.fr>
License: MIT license
Project-URL: Homepage, https://git.afpy.org/AFPy/pospell
Keywords: po,spell,gettext,reStructuredText,check,sphinx,translation
Classifier: Development Status :: 5 - Production/Stable
Classifier: Intended Audience :: Developers
Classifier: License :: OSI Approved :: MIT License
Classifier: Natural Language :: English
Classifier: Programming Language :: Python :: 3
Requires-Python: >=3.6
Requires-Dist: polib
Requires-Dist: docutils (>=0.18)
Requires-Dist: regex
Requires-Dist: sphinx-lint (>=0.6.8)
